deep_utils/__init__.py
deep_utils/custom_dataset/__init__.py
deep_utils/custom_dataset/dataset.py
deep_utils/engine/__init__.py
deep_utils/engine/train.py
deep_utils/utils/__init__.py
deep_utils/utils/help_func.py
ml_dp_utils-0.0.1.dist-info/METADATA
ml_dp_utils-0.0.1.dist-info/WHEEL
ml_dp_utils-0.0.1.dist-info/top_level.txt
ml_dp_utils-0.0.1.dist-info/RECORD
